bestia/__init__.py
bestia/error.py
bestia/iterate.py
bestia/output.py
bestia-5.0.dist-info/LICENSE
bestia-5.0.dist-info/METADATA
bestia-5.0.dist-info/WHEEL
bestia-5.0.dist-info/top_level.txt
bestia-5.0.dist-info/RECORD
