Metadata-Version: 2.1
Name: bestia
Version: 5.0
Summary: A collection of tools for building dynamic Command-Line applications
Home-page: https://github.com/synestematic/bestia
Author: Federico Rizzo
Author-email: synestem@ticATgmail.com
License: MIT
Classifier: Programming Language :: Python :: 3 :: Only
Classifier: Development Status :: 5 - Production/Stable
Classifier: License :: OSI Approved :: MIT License
Classifier: Operating System :: POSIX :: Linux
Classifier: Operating System :: MacOS :: MacOS X
Classifier: Topic :: Software Development :: Libraries :: Python Modules
Classifier: Topic :: Text Processing :: General
Classifier: Topic :: Utilities
License-File: LICENSE
